multi_media_operations/__init__.py
multi_media_operations/img_operations/__init__.py
multi_media_operations/img_operations/basic_operation.py
multi_media_operations/img_operations/img_info.py
multi_media_operations/img_operations/mid_operation.py
multi_media_operations/img_operations/paddleocr_opetation.py
multi_media_operations/img_operations/qrcode_operation.py
multi_media_operations/video_operations/__init__.py
multi_media_operations/video_operations/hikvision_operations.py
multi_media_operations/video_operations/video_operation.py
multi_media_operations-0.0.6.dist-info/LICENSE
multi_media_operations-0.0.6.dist-info/METADATA
multi_media_operations-0.0.6.dist-info/WHEEL
multi_media_operations-0.0.6.dist-info/top_level.txt
multi_media_operations-0.0.6.dist-info/RECORD
